zeratool/__init__.py
zeratool/formatDetector.py
zeratool/formatExploiter.py
zeratool/formatLeak.py
zeratool/inputDetector.py
zeratool/malloc_model.py
zeratool/overflowDetector.py
zeratool/overflowExploitSender.py
zeratool/overflowExploiter.py
zeratool/printf_model.py
zeratool/protectionDetector.py
zeratool/puts_model.py
zeratool/radare_helper.py
zeratool/simgr_helper.py
zeratool/winFunctionDetector.py
zeratool-2.1.data/scripts/zerapwn.py
zeratool-2.1.dist-info/LICENSE
zeratool-2.1.dist-info/METADATA
zeratool-2.1.dist-info/WHEEL
zeratool-2.1.dist-info/top_level.txt
zeratool-2.1.dist-info/RECORD
